xia_compiler_python/__init__.py
xia_compiler_python/compiler.cp310-win_amd64.pyd
xia_compiler_python-0.1.8.dist-info/LICENSE.txt
xia_compiler_python-0.1.8.dist-info/METADATA
xia_compiler_python-0.1.8.dist-info/WHEEL
xia_compiler_python-0.1.8.dist-info/top_level.txt
xia_compiler_python-0.1.8.dist-info/RECORD
