Metadata-Version: 2.1
Name: xia-compiler-python
Version: 0.1.8
Home-page: https://develop.x-i-a.com/docs/xia-compiler-python/0.1.8/index.html
Author: X-I-A
Author-email: admin@x-i-a.com
Requires-Python: >=3.9
License-File: LICENSE.txt
Requires-Dist: xia-engine
